DataSpyre-0.2.8.dist-info/DESCRIPTION.rst
DataSpyre-0.2.8.dist-info/METADATA
DataSpyre-0.2.8.dist-info/RECORD
DataSpyre-0.2.8.dist-info/WHEEL
DataSpyre-0.2.8.dist-info/metadata.json
DataSpyre-0.2.8.dist-info/pbr.json
DataSpyre-0.2.8.dist-info/top_level.txt
spyre/View.py
spyre/__init__.py
spyre/banner.html
spyre/example_show_all_the_inputs.py
spyre/model.py
spyre/server.py
spyre/tezt_app2.py
spyre/view.html
spyre/public/css/style.css
spyre/public/images/loading_wheel.gif
spyre/public/js/d3.v3.js
spyre/public/js/jquery-2.0.3.min.js
spyre/public/js/sorttable.js
spyre/public/js/spyre.js
