Metadata-Version: 2.0
Name: DataSpyre
Version: 0.2.8
Summary: Spyre makes it easy to build interactive web applications,and requires no knowledge of HTML, CSS, or Javascript.
Home-page: https://github.com/adamhajari/spyre
Author: Adam Hajari
Author-email: adam@nextbigsound.com
License: MIT
Keywords: web application template data visualization
Platform: UNKNOWN
Classifier: Development Status :: 4 - Beta
Classifier: Framework :: CherryPy
Classifier: Intended Audience :: Education
Classifier: Intended Audience :: Science/Research
Classifier: Environment :: Web Environment
Classifier: Topic :: Scientific/Engineering
Classifier: License :: OSI Approved :: MIT License
Classifier: Programming Language :: Python :: 2.7
Classifier: Programming Language :: Python :: 3.4
Requires-Dist: six (>=1.11.0)
Requires-Dist: numpy
Requires-Dist: pandas
Requires-Dist: cherrypy
Requires-Dist: jinja2
Requires-Dist: matplotlib
